fmake/Convert2CSV.py
fmake/__init__.py
fmake/entity_to_data_frame.py
fmake/export_registers_from_csv.py
fmake/extract_files.py
fmake/generic_helper.py
fmake/get_help.py
fmake/main_vhdl_make.py
fmake/make_bash_bindings.py
fmake/make_build_system.py
fmake/make_powershell_bindings.py
fmake/make_test_bench_stimulus.py
fmake/make_timestamps.py
fmake/mdPyEx.py
fmake/run_ise.py
fmake/send_axi_stream_udp.py
fmake/text_io_query.py
fmake/user_program_runner.py
fmake/vhdl_dependency_db.py
fmake/vhdl_entity_class.py
fmake/vhdl_get_entity_def.py
fmake/vhdl_get_list_of_files.py
fmake/vhdl_get_type_def.py
fmake/vhdl_load_file_without_comments.py
fmake/vhdl_make_implementation.py
fmake/vhdl_make_simulation.py
fmake/vhdl_make_test_bench.py
fmake/vhdl_make_test_bench_names.py
fmake/vhdl_merge_split_test_cases.py
fmake/vhdl_parser.py
fmake/vhdl_programm_list.py
fmake/vhdl_run_vivado.py
fmake/makeise/__init__.py
fmake/makeise/makePrj.py
fmake/makeise/makeise.py
fmake/vhdl_csv_io/CSV_UtilityPkg.py
fmake/vhdl_csv_io/ClockGenerator.py
fmake/vhdl_csv_io/__init__.py
fmake/vhdl_csv_io/csv_register_interface.py
fmake/vhdl_csv_io/csv_text_io_poll.py
fmake/vhdl_csv_io/e_csv_read_file.py
fmake/vhdl_csv_io/e_csv_write_file.py
fmake/vhdl_csv_io/type_conversions_helper.py
fmake-0.2.6.dist-info/METADATA
fmake-0.2.6.dist-info/WHEEL
fmake-0.2.6.dist-info/entry_points.txt
fmake-0.2.6.dist-info/top_level.txt
fmake-0.2.6.dist-info/RECORD
