Metadata-Version: 2.4
Name: fmake
Version: 0.2.6
Summary: build scripts for firmware projects
Home-page: 
Author: Richard Peschke
Author-email: peschke@hawaii.edu
Classifier: Programming Language :: Python :: 3
Classifier: License :: OSI Approved :: MIT License
Classifier: Operating System :: OS Independent
Requires-Python: >=3.8
Requires-Dist: pandas
Requires-Dist: numpy
Requires-Dist: matplotlib
Requires-Dist: wget
Requires-Dist: openpyxl
Requires-Dist: dataframe_helpers
Dynamic: author
Dynamic: author-email
Dynamic: classifier
Dynamic: description
Dynamic: description-content-type
Dynamic: requires-dist
Dynamic: requires-python
Dynamic: summary
